deka/__init__.py
deka/config.py
deka/core.py
deka/exceptions.py
deka/language_mapper.py
deka/models.py
deka/utils.py
deka/providers/__init__.py
deka/providers/anthropic.py
deka/providers/base.py
deka/providers/deepl.py
deka/providers/gemini.py
deka/providers/ghananlp.py
deka/providers/google.py
deka/providers/openai.py
deka-0.1.0.dist-info/METADATA
deka-0.1.0.dist-info/WHEEL
deka-0.1.0.dist-info/licenses/LICENSE
deka-0.1.0.dist-info/RECORD
