Metadata-Version: 2.4
Name: deka
Version: 0.1.0
Summary: A unified Python SDK for multiple translation providers
Project-URL: Homepage, https://deka-website.vercel.app/
Project-URL: Repository, https://github.com/FrejusGdm/deka-project
Project-URL: Documentation, https://deka.readthedocs.io
Project-URL: Issues, https://github.com/FrejusGdm/deka-project/issues
Author-email: Josue Godeme <gjf7075@gmail.com>
License-Expression: MIT
License-File: LICENSE
Keywords: api,deepl,google-translate,multilingual,openai,translation
Classifier: Development Status :: 3 - Alpha
Classifier: Intended Audience :: Developers
Classifier: License :: OSI Approved :: MIT License
Classifier: Programming Language :: Python :: 3
Classifier: Programming Language :: Python :: 3.8
Classifier: Programming Language :: Python :: 3.9
Classifier: Programming Language :: Python :: 3.10
Classifier: Programming Language :: Python :: 3.11
Classifier: Programming Language :: Python :: 3.12
Classifier: Topic :: Software Development :: Libraries :: Python Modules
Classifier: Topic :: Text Processing :: Linguistic
Requires-Python: >=3.8
Requires-Dist: aiohttp>=3.8.0
Requires-Dist: google-genai>=0.8.0
Requires-Dist: pydantic>=1.8.0
Requires-Dist: python-dotenv>=0.19.0
Requires-Dist: requests>=2.25.0
Provides-Extra: dev
Requires-Dist: black>=22.0; extra == 'dev'
Requires-Dist: build>=0.8.0; extra == 'dev'
Requires-Dist: flake8>=4.0; extra == 'dev'
Requires-Dist: mypy>=0.950; extra == 'dev'
Requires-Dist: pytest-asyncio>=0.18.0; extra == 'dev'
Requires-Dist: pytest>=6.0; extra == 'dev'
Requires-Dist: twine>=4.0.0; extra == 'dev'
Provides-Extra: docs
Requires-Dist: mkdocs-material>=9.0.0; extra == 'docs'
Requires-Dist: mkdocs>=1.5.0; extra == 'docs'
Requires-Dist: mkdocstrings[python]>=0.20.0; extra == 'docs'
